LICENSE
MANIFEST.in
README.md
requirements.txt
setup.py
glycogenius_GUI/File_Editor.py
glycogenius_GUI/GG_Draw.py
glycogenius_GUI/GUI.py
glycogenius_GUI/GUI_refactor.py
glycogenius_GUI/Splash_Screen.py
glycogenius_GUI/__init__.py
glycogenius_GUI/__main__.py
glycogenius_GUI.egg-info/PKG-INFO
glycogenius_GUI.egg-info/SOURCES.txt
glycogenius_GUI.egg-info/dependency_links.txt
glycogenius_GUI.egg-info/entry_points.txt
glycogenius_GUI.egg-info/requires.txt
glycogenius_GUI.egg-info/top_level.txt
glycogenius_GUI/Assets/antennas_n.gga
glycogenius_GUI/Assets/antennas_o.gga
glycogenius_GUI/Assets/back_arrow.png
glycogenius_GUI/Assets/banner.png
glycogenius_GUI/Assets/eic.png
glycogenius_GUI/Assets/gg_draw.png
glycogenius_GUI/Assets/gg_draw_off.png
glycogenius_GUI/Assets/gg_icon.ico
glycogenius_GUI/Assets/heatmap_small.png
glycogenius_GUI/Assets/logo.png
glycogenius_GUI/Assets/mis.png
glycogenius_GUI/Assets/next_arrow.png
glycogenius_GUI/Assets/remove_ruler_small.png
glycogenius_GUI/Assets/right_arrow.png
glycogenius_GUI/Assets/ruler.png
glycogenius_GUI/Assets/ruler_small.png
glycogenius_GUI/Assets/spectra_edit.png
glycogenius_GUI/Assets/splash.png
glycogenius_GUI/Assets/zoom_lock.png